{
    "enabled": true,
    "coin": "verium.json",
    "daemon": {
        "port": 33987,
        "username": "veriumrpc",
        "password": "2Z9MAhm2sk3A8mBJ8AnSuQpVkgjxE3qgWWsHefbnkpy3"
    },
    "wallet": {
        "address": "VQFbP6oEXXQZ4bhADqRnYYFXtg7QYvLNf3"
    },
    "rewards": [
        {
            "VUVgeLFGqdFqqaUksz8bpoEQQZQSJMWVtX": 1
        }
    ],
    "stratum": {
        "port": 3336
    },
    "storage": {
        "hybrid": {
            "mysql": {
                "database": "hashpool_one_vrc"
            }
        }
    }
}
